README.rst
setup.cfg
setup.py
cross_river_bank/__init__.py
cross_river_bank.egg-info/PKG-INFO
cross_river_bank.egg-info/SOURCES.txt
cross_river_bank.egg-info/dependency_links.txt
cross_river_bank.egg-info/not-zip-safe
cross_river_bank.egg-info/requires.txt
cross_river_bank.egg-info/top_level.txt