Metadata-Version: 1.1
Name: cross-river-bank
Version: 1.0.16
Summary: Cross River Bank API Python client
Home-page: https://www.crossriverbank.com/
Author: Cross River Bank
Author-email: support@crossriverbank.com
License: MIT License
Platform: UNKNOWN
Classifier: Intended Audience :: Developers
Classifier: License :: OSI Approved :: MIT License
Classifier: Programming Language :: Python
Classifier: Topic :: Software Development :: Libraries :: Python Modules
